ActionStreamerWS/__init__.py
ActionStreamerWS/ActionStreamerWS/__init__.py
ActionStreamerWS/ActionStreamerWS/API/__init__.py
ActionStreamerWS/ActionStreamerWS/API/API.py
ActionStreamerWS/ActionStreamerWS/Config/__init__.py
ActionStreamerWS/ActionStreamerWS/Config/Config.py
ActionStreamerWS/ActionStreamerWS/Device/__init__.py
ActionStreamerWS/ActionStreamerWS/Device/Device.py
ActionStreamerWS/ActionStreamerWS/Event/__init__.py
ActionStreamerWS/ActionStreamerWS/Event/Event.py
ActionStreamerWS/ActionStreamerWS/File/__init__.py
ActionStreamerWS/ActionStreamerWS/File/File.py
ActionStreamerWS/ActionStreamerWS/Health/__init__.py
ActionStreamerWS/ActionStreamerWS/Health/Health.py
ActionStreamerWS/ActionStreamerWS/Patch/__init__.py
ActionStreamerWS/ActionStreamerWS/Patch/Patch.py
ActionStreamerWS/ActionStreamerWS/VideoClip/__init__.py
ActionStreamerWS/ActionStreamerWS/VideoClip/VideoClip.py
ActionStreamerWS/CommonFunctions/__init__.py
ActionStreamerWS/CommonFunctions/CommonFunctions.py
ActionStreamerWS/CommonFunctions/Wifi/__init__.py
ActionStreamerWS/CommonFunctions/Wifi/Wifi.py
actionstreamerws-0.1.10.dist-info/METADATA
actionstreamerws-0.1.10.dist-info/WHEEL
actionstreamerws-0.1.10.dist-info/RECORD
