Metadata-Version: 2.1
Name: ActionStreamerWS
Version: 0.1.10
Summary: A library for the ActionStreamer API.
Author: ActionStreamer
Author-email: joe@actionstreamer.com
Requires-Python: >=3.10,<4.0
Classifier: Programming Language :: Python :: 3
Classifier: Programming Language :: Python :: 3.10
Classifier: Programming Language :: Python :: 3.11
Classifier: Programming Language :: Python :: 3.12
